jupyterlab_keycloak_opener/__init__.py
jupyterlab_keycloak_opener/_version.py
jupyterlab_keycloak_opener/handlers.py
jupyterlab_keycloak_opener/labextension/build_log.json
jupyterlab_keycloak_opener/labextension/package.json
jupyterlab_keycloak_opener/labextension/static/lib_index_js.edac2f1f46ef404abff2.js
jupyterlab_keycloak_opener/labextension/static/lib_index_js.edac2f1f46ef404abff2.js.map
jupyterlab_keycloak_opener/labextension/static/remoteEntry.c1fd7286b6aaacfbfefb.js
jupyterlab_keycloak_opener/labextension/static/remoteEntry.c1fd7286b6aaacfbfefb.js.map
jupyterlab_keycloak_opener/labextension/static/style.js
jupyterlab_keycloak_opener/labextension/static/style_index_js.0b0afc7db13fef69a2ad.js
jupyterlab_keycloak_opener/labextension/static/style_index_js.0b0afc7db13fef69a2ad.js.map
jupyterlab_keycloak_opener/tests/__init__.py
jupyterlab_keycloak_opener/tests/test_handlers.py
jupyterlab_keycloak_opener-0.1.40.data/data/etc/jupyter/jupyter_server_config.d/jupyterlab_keycloak_opener.json
jupyterlab_keycloak_opener-0.1.40.data/data/share/jupyter/labextensions/jupyterlab-keycloak-opener/build_log.json
jupyterlab_keycloak_opener-0.1.40.data/data/share/jupyter/labextensions/jupyterlab-keycloak-opener/package.json
jupyterlab_keycloak_opener-0.1.40.data/data/share/jupyter/labextensions/jupyterlab-keycloak-opener/static/lib_index_js.edac2f1f46ef404abff2.js
jupyterlab_keycloak_opener-0.1.40.data/data/share/jupyter/labextensions/jupyterlab-keycloak-opener/static/lib_index_js.edac2f1f46ef404abff2.js.map
jupyterlab_keycloak_opener-0.1.40.data/data/share/jupyter/labextensions/jupyterlab-keycloak-opener/static/remoteEntry.c1fd7286b6aaacfbfefb.js
jupyterlab_keycloak_opener-0.1.40.data/data/share/jupyter/labextensions/jupyterlab-keycloak-opener/static/remoteEntry.c1fd7286b6aaacfbfefb.js.map
jupyterlab_keycloak_opener-0.1.40.data/data/share/jupyter/labextensions/jupyterlab-keycloak-opener/static/style.js
jupyterlab_keycloak_opener-0.1.40.dist-info/METADATA
jupyterlab_keycloak_opener-0.1.40.dist-info/WHEEL
jupyterlab_keycloak_opener-0.1.40.dist-info/licenses/LICENSE
jupyterlab_keycloak_opener-0.1.40.dist-info/RECORD
